drf_simple_jwt_2fa/__init__.py
drf_simple_jwt_2fa/authentication.py
drf_simple_jwt_2fa/exceptions.py
drf_simple_jwt_2fa/sending.py
drf_simple_jwt_2fa/serializers.py
drf_simple_jwt_2fa/settings.py
drf_simple_jwt_2fa/throttling.py
drf_simple_jwt_2fa/token_manager.py
drf_simple_jwt_2fa/urls.py
drf_simple_jwt_2fa/utils.py
drf_simple_jwt_2fa/views.py
drf_simple_jwt_2fa/tests/__init__.py
drf_simple_jwt_2fa/tests/factories.py
drf_simple_jwt_2fa/tests/test_endpoints.py
drf_simple_jwt_2fa/tests/test_throttling.py
drf_simple_jwt_2fa/tests/test_token_manager.py
drf_simple_jwt_2fa/tests/utils.py
drf_simple_jwt_2fa-1.2.5.dist-info/LICENSE
drf_simple_jwt_2fa-1.2.5.dist-info/METADATA
drf_simple_jwt_2fa-1.2.5.dist-info/WHEEL
drf_simple_jwt_2fa-1.2.5.dist-info/top_level.txt
drf_simple_jwt_2fa-1.2.5.dist-info/RECORD
