Metadata-Version: 2.1
Name: drf-simple-jwt-2fa
Version: 1.2.5
Summary: Django Rest Framework Simple JWT 2FA
Home-page: https://github.com/GauthierSgds/drf-simple-jwt-2fa
Maintainer: Gauthier Segonds
Maintainer-email: gauthier.segonds@lugos.fr
License: MIT
Keywords: Authentication,Two Factor,Django Rest Framework,JSON Web Token,Simple JWT
Platform: any
Classifier: Development Status :: 4 - Beta
Classifier: Environment :: Web Environment
Classifier: Framework :: Django
Classifier: Framework :: Django :: 3.0
Classifier: Intended Audience :: Developers
Classifier: Operating System :: OS Independent
Classifier: Programming Language :: Python :: 3.7
Classifier: Topic :: Internet :: WWW/HTTP :: Session
License-File: LICENSE
Requires-Dist: djangorestframework-simplejwt
